{
  "meta":{
  "name": "OpenFOAM",
  "rank": "0",
  "size": "1",
  "unix_us": "1739742357846101",
  "tinit": "2025-02-16T22:45:57.101",
  "mode": "fundamental"
  },
  "events":[
  {"et":"n","en":"construction","eid":0},{"et":"b","eid":0,"ts":42},{"et":"n","en":"construction/configure","eid":1},{"et":"b","eid":1,"ts":49},{"et":"e","eid":1,"ts":14492},{"et":"n","en":"construction/startProfilingBackend","eid":2},{"et":"n","en":"_GLOBAL","eid":3},{"et":"b","eid":3,"ts":0},{"et":"e","eid":0,"ts":14864},{"et":"n","en":"solver.initialize","eid":4},{"et":"b","eid":4,"ts":14885},{"et":"e","eid":4,"ts":12818847},{"et":"n","en":"initialize","eid":5},{"et":"b","eid":5,"ts":12818866},{"et":"n","en":"initialize/preprocess.FOAM_Sides","eid":6},{"et":"n","en":"initialize/preprocess.FOAM_Top","eid":7},{"et":"n","en":"initialize/m2n.requestPrimaryRankConnection.SWEET","eid":8},{"et":"b","eid":8,"ts":12819004},{"et":"e","eid":8,"ts":12819394},{"et":"n","en":"initialize/partition.prepareMesh.FOAM_Sides","eid":9},{"et":"n","en":"initialize/partition.prepareMesh.FOAM_Top","eid":10},{"et":"n","en":"initialize/partition.receiveGlobalMesh.SWE_Sides","eid":11},{"et":"n","en":"initialize/partition.receiveGlobalMesh.SWE_Top","eid":12},{"et":"n","en":"initialize/m2n.requestSecondaryRanksConnection","eid":13},{"et":"n","en":"initialize/m2n.exchangeVertexDistribution","eid":14},{"et":"n","en":"initialize/m2n.broadcastVertexDistributions","eid":15},{"et":"n","en":"initialize/m2n.buildCommunicationMap","eid":16},{"et":"n","en":"initialize/m2n.createCommunications","eid":17},{"et":"n","en":"initialize/map.nn.computeMapping.FromFOAM_TopToSWE_Top","eid":18},{"et":"n","en":"initialize/query.index.getVertexIndexTree.FOAM_Top","eid":19},{"et":"n","en":"initialize/map.nn.mapData.FromFOAM_TopToSWE_Top","eid":20},{"et":"n","en":"initialize/m2n.sendData","eid":21},{"et":"n","en":"initialize/m2n.receiveData","eid":22},{"et":"n","en":"initialize/map.nn.computeMapping.FromSWE_SidesToFOAM_Sides","eid":23},{"et":"n","en":"initialize/query.index.getVertexIndexTree.SWE_Sides","eid":24},{"et":"n","en":"initialize/map.nn.mapData.FromSWE_SidesToFOAM_Sides","eid":25},{"et":"e","eid":5,"ts":19953266},{"et":"n","en":"solver.advance","eid":26},{"et":"b","eid":26,"ts":19953321},{"et":"e","eid":26,"ts":21732760},{"et":"n","en":"advance","eid":27},{"et":"b","eid":27,"ts":21732779},{"et":"n","en":"advance/map.nn.mapData.FromFOAM_TopToSWE_Top","eid":28},{"et":"n","en":"advance/m2n.sendData","eid":29},{"et":"n","en":"advance/m2n.receiveData","eid":30},{"et":"n","en":"advance/map.nn.mapData.FromSWE_SidesToFOAM_Sides","eid":31},{"et":"e","eid":27,"ts":22399615},{"et":"b","eid":26,"ts":22399624},{"et":"e","eid":26,"ts":23616229},{"et":"b","eid":27,"ts":23616246},{"et":"e","eid":27,"ts":34473024},{"et":"b","eid":26,"ts":34473181},{"et":"e","eid":26,"ts":35799546},{"et":"b","eid":27,"ts":35799562},{"et":"e","eid":27,"ts":38154210},{"et":"b","eid":26,"ts":38154220},{"et":"e","eid":26,"ts":39406040},{"et":"b","eid":27,"ts":39406055},{"et":"e","eid":27,"ts":59008790},{"et":"b","eid":26,"ts":59008800},{"et":"e","eid":26,"ts":60293639},{"et":"b","eid":27,"ts":60293657},{"et":"e","eid":27,"ts":67188710},{"et":"b","eid":26,"ts":67188721},{"et":"e","eid":26,"ts":68456767},{"et":"b","eid":27,"ts":68456784},{"et":"e","eid":27,"ts":73187793},{"et":"b","eid":26,"ts":73187809},{"et":"e","eid":26,"ts":74452012},{"et":"b","eid":27,"ts":74452032},{"et":"e","eid":27,"ts":75709098},{"et":"b","eid":26,"ts":75709109},{"et":"e","eid":26,"ts":77015976},{"et":"b","eid":27,"ts":77015993},{"et":"e","eid":27,"ts":81374847},{"et":"b","eid":26,"ts":81374858},{"et":"e","eid":26,"ts":82639069},{"et":"b","eid":27,"ts":82639085},{"et":"e","eid":27,"ts":84200278},{"et":"b","eid":26,"ts":84200288},{"et":"e","eid":26,"ts":85473855},{"et":"b","eid":27,"ts":85473871},{"et":"e","eid":27,"ts":85712104},{"et":"b","eid":26,"ts":85712118},{"et":"e","eid":26,"ts":87012608},{"et":"b","eid":27,"ts":87012627},{"et":"e","eid":27,"ts":88251745},{"et":"b","eid":26,"ts":88251756},{"et":"e","eid":26,"ts":89544541},{"et":"b","eid":27,"ts":89544558},{"et":"e","eid":27,"ts":91973967},{"et":"b","eid":26,"ts":91973981},{"et":"e","eid":26,"ts":93235690},{"et":"b","eid":27,"ts":93235706},{"et":"e","eid":27,"ts":93855017},{"et":"b","eid":26,"ts":93855032},{"et":"e","eid":26,"ts":95181602},{"et":"b","eid":27,"ts":95181619},{"et":"e","eid":27,"ts":101469130},{"et":"b","eid":26,"ts":101469141},{"et":"e","eid":26,"ts":102824294},{"et":"b","eid":27,"ts":102824311}